proctor_exam/__init__.py
proctor_exam/proctor_exam.py
proctor_exam/locale/fr/LC_MESSAGES/django.mo
proctor_exam/locale/fr/LC_MESSAGES/django.po
proctor_exam/public/images/banner.png
proctor_exam/public/images/chrome-logo.png
proctor_exam/public/images/warning-icon.png
proctor_exam/static/css/student.css
proctor_exam/static/html/honor.html
proctor_exam/static/html/sequence.html
proctor_exam/static/html/student.html
proctor_exam/static/html/studio.html
xblock_proctor_exam-1.0.0.dist-info/LICENSE
xblock_proctor_exam-1.0.0.dist-info/METADATA
xblock_proctor_exam-1.0.0.dist-info/WHEEL
xblock_proctor_exam-1.0.0.dist-info/entry_points.txt
xblock_proctor_exam-1.0.0.dist-info/top_level.txt
xblock_proctor_exam-1.0.0.dist-info/RECORD
