Metadata-Version: 2.1
Name: xblock-proctor-exam
Version: 1.0.0
Summary: Xblock restricting access to course test to Proctor Exam monitoring process.
Home-page: https://github.com/openfun/xblock-proctor-exam
Author: Open FUN (France Universite Numérique)
Author-email: fun.dev@fun-mooc.fr
License: AGPL 3.0
Keywords: Django,Open edX,MOOC,Xblock,proctoring
Platform: UNKNOWN
Classifier: Development Status :: 4 - Beta
Classifier: Framework :: Django
Classifier: Framework :: Django :: 1.8
Classifier: Intended Audience :: Developers
Classifier: License :: OSI Approved :: GNU Affero General Public License v3 or later (AGPLv3+)
Classifier: Natural Language :: English
Classifier: Programming Language :: Python :: 2
Classifier: Programming Language :: Python :: 2.7
Requires-Dist: XBlock
Requires-Dist: XBlock-utils
Requires-Dist: configurable-lti-consumer-xblock
Provides-Extra: dev
Requires-Dist: twine (==1.11.0) ; extra == 'dev'
